NsgOrcFx/__init__.py
NsgOrcFx/auxfuncs.py
NsgOrcFx/classes.py
NsgOrcFx/constants.py
NsgOrcFx/constraintloads.py
NsgOrcFx/environment.py
NsgOrcFx/fatigue.py
NsgOrcFx/loadcases.py
NsgOrcFx/main.py
NsgOrcFx/modal.py
NsgOrcFx/multiproc.py
NsgOrcFx/objauxfuncs.py
NsgOrcFx/params.py
NsgOrcFx/raos.py
NsgOrcFx/raos_old.py
NsgOrcFx/sncurves.py
NsgOrcFx/sortlines.py
NsgOrcFx/utils.py
NsgOrcFx/vessel.py
NsgOrcFx/weight.py
NsgOrcFx/weightaux.py
nsgorcfx-1.0.35.dist-info/licenses/LICENSE
nsgorcfx-1.0.35.dist-info/METADATA
nsgorcfx-1.0.35.dist-info/WHEEL
nsgorcfx-1.0.35.dist-info/top_level.txt
nsgorcfx-1.0.35.dist-info/RECORD
