Metadata-Version: 2.4
Name: NsgOrcFx
Version: 1.0.35
Summary: Package with additional tools to the OrcFxAPI package
Author-email: NSG Engenharia <software@nsgeng.com>
Project-URL: Homepage, https://github.com/NSG-Engenharia/NsgOrcFx
Project-URL: Issues, https://github.com/NSG-Engenharia/NsgOrcFx/issues
Classifier: Programming Language :: Python :: 3
Classifier: License :: OSI Approved :: MIT License
Classifier: Operating System :: Microsoft :: Windows
Requires-Python: >=3.8
License-File: LICENSE
Requires-Dist: OrcFxAPI>=11.4.2
Requires-Dist: numpy>=1.26.4
Requires-Dist: pandas>=2.2.2
Requires-Dist: scipy>=1.13.0
Requires-Dist: matplotlib>=3.8.0
Dynamic: license-file
